<?xml version="1.0" encoding="UTF-8"?>
<objects serializationModel="Studio.02.00.00">
	<object class="AudioFile" id="{8628abf0-1b4c-4073-a52f-d3ed26159a0f}">
		<property name="assetPath">
			<value>Cutscene_Post_Level_1_DRAFT_2.mp3</value>
		</property>
		<property name="isStreaming">
			<value>true</value>
		</property>
		<property name="frequencyInKHz">
			<value>44.0999985</value>
		</property>
		<property name="channelCount">
			<value>2</value>
		</property>
		<property name="length">
			<value>73.717551020408166</value>
		</property>
		<relationship name="masterAssetFolder">
			<destination>{46819244-2823-4e66-a366-ead6616856c9}</destination>
		</relationship>
	</object>
</objects>
