<?xml version="1.0" encoding="UTF-8"?>
<objects serializationModel="Studio.02.00.00">
	<object class="AudioFile" id="{876bca72-ade6-4c7c-a3fc-2952f5ea0a67}">
		<property name="assetPath">
			<value>GalbraithHall.wav</value>
		</property>
		<property name="frequencyInKHz">
			<value>44.0999985</value>
		</property>
		<property name="channelCount">
			<value>2</value>
		</property>
		<property name="length">
			<value>0.86374149659863941</value>
		</property>
		<relationship name="masterAssetFolder">
			<destination>{46819244-2823-4e66-a366-ead6616856c9}</destination>
		</relationship>
	</object>
</objects>
